randomit/__init__.py
randomit/parsers/random_images.py
randomit/randomizer.py
randomit/words_storage/addresses_list.txt
randomit/words_storage/cities_list.txt
randomit/words_storage/countries_list.txt
randomit/words_storage/names_list.txt
randomit/words_storage/random_words.txt
randomit/words_storage/surnames_list.txt
randomit-0.2.7.dist-info/LICENSE
randomit-0.2.7.dist-info/WHEEL
randomit-0.2.7.dist-info/METADATA
randomit-0.2.7.dist-info/RECORD
